etc/pallas.config
pallas_trace/__init__.py
pallas_trace/__init__.pyi
pallas_trace/_core.cpython-314-x86_64-linux-gnu.so
pallas_trace.libs/libzstd-d01e4fcb.so.1.5.7
pallas_trace-0.17.0.dist-info/METADATA
pallas_trace-0.17.0.dist-info/WHEEL
pallas_trace-0.17.0.dist-info/RECORD
pallas_trace-0.17.0.dist-info/licenses/LICENSE
