Metadata-Version: 2.4
Name: pallas_trace
Version: 0.17.0
Summary: Pallas is a scalable trace format for HPC applications.
Author-Email: Catherine Guelque <catherine.guelque@telecom-sudparis.eu>, Francois Trahay <francois.trahay@telecom-sudparis.eu>, Valentin Delis <valentin.delis@ensiie.fr>, Louis Delyon <louis_delyon@telecom-sudparis.eu>
License-Expression: BSD-3-Clause
License-File: LICENSE
Classifier: Programming Language :: Python :: 3
Classifier: Operating System :: Unix
Project-URL: Homepage, https://gitlab.inria.fr/pallas/pallas
Project-URL: Issues, https://gitlab.inria.fr/pallas/pallas/issues
Requires-Python: >=3.8
